octdata4python/__init__.py
octdata4python/core/octdata4python.pyd
octdata4python/core/read.py
octdata4python/core/__init__.py
octdata4python-0.1.2.dist-info/DELVEWHEEL
octdata4python-0.1.2.dist-info/METADATA
octdata4python-0.1.2.dist-info/RECORD
octdata4python-0.1.2.dist-info/WHEEL
octdata4python-0.1.2.dist-info/licenses/license.txt
octdata4python.libs/boost_filesystem-vc143-mt-x64-1_88-dc0fae806e711ee7adf037c34195dde0.dll
octdata4python.libs/boost_locale-vc143-mt-x64-1_88-93495bfede24ed35a9d97afe65a4adaa.dll
octdata4python.libs/boost_log-vc143-mt-x64-1_88-e4c495145561aadf67b9377276e4950b.dll
octdata4python.libs/boost_numpy311-vc143-mt-x64-1_88-cfd68fca6d3c9e8e2363d7735ec6a4bc.dll
octdata4python.libs/boost_python311-vc143-mt-x64-1_88-56ec4bfde3a12e195855537bda65b7e1.dll
octdata4python.libs/boost_thread-vc143-mt-x64-1_88-b2161aa74186da171c6430798de3f851.dll
octdata4python.libs/concrt140-8569fdea54705f11a7adae12c8e05034.dll
octdata4python.libs/dcmdata-332ab0bc6bcffa1c6f0c675e484f7b4e.dll
octdata4python.libs/msvcp140-9b229e34469d863c7a5168a990c321a4.dll
octdata4python.libs/msvcp140_codecvt_ids-176840d2b9118589e1c6b20a7d31980e.dll
octdata4python.libs/octdata-4526d77893549e8ed9008906e71d61a5.dll
octdata4python.libs/oficonv-12b3748222285fa30981592d02ba8c01.dll
octdata4python.libs/oflog-f88ecc7e9a134cd9238189f45dac7fd2.dll
octdata4python.libs/ofstd-33592be2c9a2ed20ffd2bc9f6d5e06ac.dll
octdata4python.libs/opencv_world4110-ae7314d40b6b789a2bb343aaabb9a8dc.dll
octdata4python.libs/openjp2-56cfe52fe9c65f576223bbdd986f328f.dll
octdata4python.libs/tiff-0422aa558c53dc5e1b3fb7504ded7fff.dll
octdata4python.libs/zlib-d272b5f435de39910c8d805452f1fe2c.dll
